fastapi_essentials/__init__.py
fastapi_essentials/logging.py
fastapi_essentials/main.py
fastapi_essentials/middleware.py
fastapi_essentials/py.typed
fastapi_essentials-0.2.2.dist-info/METADATA
fastapi_essentials-0.2.2.dist-info/WHEEL
fastapi_essentials-0.2.2.dist-info/RECORD
