Metadata-Version: 2.3
Name: fastapi_essentials
Version: 0.2.2
Summary: fastapi plugin to register common functionality
Requires-Python: >=3.10
Requires-Dist: asgi-correlation-id>=4.3.1
Requires-Dist: fastapi>=0.111.1
Requires-Dist: python-json-logger>=2.0.7
